{
  "_updated": "2026-04-23",
  "_sources": {
    "eu_27": "EU Oil Bulletin via fuel-prices.eu (CC BY 4.0)",
    "hr": "Government of Croatia via cijenegoriva.info (updated every 14 days)",
    "balkan": "Manual via balkan-manual.json (last edit 2026-04-21)"
  },
  "_auto_updated": "2026-04-23T19:58:49.880Z",
  "_notes": "Prices are national weekly averages including all taxes. Highway stations may charge 10-25% more.",
  "prices": {
    "MT": {
      "petrol": 1.34,
      "diesel": 1.21
    },
    "PL": {
      "petrol": 1.414,
      "diesel": 1.636
    },
    "BG": {
      "petrol": 1.47,
      "diesel": 1.756
    },
    "ES": {
      "petrol": 1.517,
      "diesel": 1.808
    },
    "CY": {
      "petrol": 1.531,
      "diesel": 1.868
    },
    "RO": {
      "petrol": 1.618,
      "diesel": 1.814
    },
    "SI": {
      "petrol": 1.647,
      "diesel": 1.874
    },
    "HU": {
      "petrol": 1.651,
      "diesel": 1.715
    },
    "CZ": {
      "petrol": 1.672,
      "diesel": 1.756
    },
    "AT": {
      "petrol": 1.691,
      "diesel": 1.948
    },
    "SK": {
      "petrol": 1.694,
      "diesel": 1.772
    },
    "LT": {
      "petrol": 1.705,
      "diesel": 2.041
    },
    "HR": {
      "petrol": 1.64,
      "diesel": 1.78
    },
    "SE": {
      "petrol": 1.716,
      "diesel": 2.017
    },
    "EE": {
      "petrol": 1.717,
      "diesel": 1.878
    },
    "LU": {
      "petrol": 1.721,
      "diesel": 1.872
    },
    "IT": {
      "petrol": 1.763,
      "diesel": 2.115
    },
    "LV": {
      "petrol": 1.791,
      "diesel": 2.006
    },
    "BE": {
      "petrol": 1.835,
      "diesel": 2.193
    },
    "PT": {
      "petrol": 1.899,
      "diesel": 1.98
    },
    "IE": {
      "petrol": 1.907,
      "diesel": 2.153
    },
    "FI": {
      "petrol": 1.961,
      "diesel": 2.246
    },
    "FR": {
      "petrol": 2.023,
      "diesel": 2.244
    },
    "DE": {
      "petrol": 2.106,
      "diesel": 2.133
    },
    "DK": {
      "petrol": 2.219,
      "diesel": 2.221
    },
    "NL": {
      "petrol": 2.279,
      "diesel": 2.296
    },
    "BA": {
      "petrol": 1.38,
      "diesel": 1.71
    },
    "RS": {
      "petrol": 1.42,
      "diesel": 1.61
    },
    "ME": {
      "petrol": 1.55,
      "diesel": 1.65
    },
    "MK": {
      "petrol": 1.48,
      "diesel": 1.55
    },
    "AL": {
      "petrol": 1.56,
      "diesel": 1.63
    },
    "XK": {
      "petrol": 1.3,
      "diesel": 1.35
    },
    "CH": {
      "petrol": 1.85,
      "diesel": 2.05
    },
    "NO": {
      "petrol": 2.2,
      "diesel": 2.3
    },
    "UK": {
      "petrol": 1.68,
      "diesel": 1.8
    },
    "TR": {
      "petrol": 1.35,
      "diesel": 1.4
    },
    "UA": {
      "petrol": 1.25,
      "diesel": 1.35
    },
    "MD": {
      "petrol": 1.3,
      "diesel": 1.35
    },
    "GE": {
      "petrol": 1.1,
      "diesel": 1.25
    }
  },
  "hr_live": {
    "validFrom": "23.4.2026",
    "companies": {
      "petrol": [
        {
          "name": "AdriaOil",
          "price": 1.64,
          "min": 1.44,
          "max": 1.66,
          "top": true,
          "variant": "EUROSUPER 95"
        },
        {
          "name": "INA",
          "price": 1.64,
          "min": 1.64,
          "max": 1.66,
          "top": true,
          "variant": "EUROSUPER 95 CLASS PLUS"
        },
        {
          "name": "Lukoil",
          "price": 1.64,
          "min": 1.64,
          "max": 1.66,
          "top": true,
          "variant": "Eurosuper BS 95"
        },
        {
          "name": "Petrol",
          "price": 1.64,
          "min": 1.64,
          "max": 1.66,
          "top": true,
          "variant": "Q MAX EUROSUPER 95"
        },
        {
          "name": "Shell",
          "price": 1.64,
          "min": 1.42,
          "max": 1.64,
          "top": true,
          "variant": "Shell Fuelsave EuroSuper 95"
        },
        {
          "name": "Tifon",
          "price": 1.64,
          "min": 0,
          "max": 1.66,
          "top": true,
          "variant": "EVO Eurosuper 95 BS"
        }
      ],
      "diesel": [
        {
          "name": "AdriaOil",
          "price": 1.78,
          "min": 1.36,
          "max": 1.85,
          "top": true,
          "variant": "EURODIESEL"
        },
        {
          "name": "INA",
          "price": 1.78,
          "min": 1.78,
          "max": 1.85,
          "top": true,
          "variant": "EURODIZEL CLASS PLUS"
        },
        {
          "name": "Lukoil",
          "price": 1.78,
          "min": 1.78,
          "max": 1.85,
          "top": true,
          "variant": "Eurodiesel BS"
        },
        {
          "name": "Petrol",
          "price": 1.78,
          "min": 1.78,
          "max": 1.85,
          "top": true,
          "variant": "EURODIZEL AD B7"
        },
        {
          "name": "Shell",
          "price": 1.78,
          "min": 1.43,
          "max": 1.78,
          "top": true,
          "variant": "Shell Fuelsave EuroDiesel"
        },
        {
          "name": "Tifon",
          "price": 1.78,
          "min": 1.78,
          "max": 1.85,
          "top": true,
          "variant": "EVO Eurodiesel BS"
        }
      ]
    },
    "source": "cijenegoriva.info",
    "updatedAt": "2026-04-23T19:58:49.880Z"
  }
}
